Tipo-Modules/Functional.py
Tipo-Modules/Node.py
Tipo-Modules/__init__.py
tipo/Functional.py
tipo/Modules.py
tipo/__init__.py
Tipo-0.0.63.dist-info/LICENSE
Tipo-0.0.63.dist-info/METADATA
Tipo-0.0.63.dist-info/WHEEL
Tipo-0.0.63.dist-info/top_level.txt
Tipo-0.0.63.dist-info/RECORD
